brave_leo/__init__.py
brave_leo/main.py
brave_leo/models.py
brave_leo-0.1.4.dist-info/LICENSE
brave_leo-0.1.4.dist-info/METADATA
brave_leo-0.1.4.dist-info/WHEEL
brave_leo-0.1.4.dist-info/top_level.txt
brave_leo-0.1.4.dist-info/RECORD
