Metadata-Version: 2.1
Name: brave-leo
Version: 0.1.4
Summary: Python wrapper for Brave's Leo AI chat functionality based on Llama
Home-page: https://github.com/KohnoseLami/brave-leo
Author: Kohnose Lami
Author-email: info@lami.zip
Classifier: License :: OSI Approved :: MIT License
Classifier: Programming Language :: Python :: 3
Classifier: Programming Language :: Python :: 3.6
Classifier: Programming Language :: Python :: 3.7
Classifier: Programming Language :: Python :: 3.8
Classifier: Programming Language :: Python :: 3.9
Classifier: Programming Language :: Python :: 3.10
Requires-Python: >=3.6
License-File: LICENSE
Requires-Dist: requests
